satute/arguments.py
satute/categories.py
satute/cli.py
satute/container/testResultBranch.py
satute/container/testStatisticComponent.py
satute/exceptions.py
satute/handler/file_handler.py
satute/handler/iqtree_handler.py
satute/logging_utils.py
satute/messages/messages.py
satute/models/amino_acid_models.py
satute/models/dna_models.py
satute/models/substitution_model.py
satute/ostream.py
satute/parser/base_parser.py
satute/parser/iqtree_aa_parser.py
satute/parser/iqtree_nucleotide_parser.py
satute/parser/iqtree_parser.py
satute/partial_likelihood/graph.py
satute/partial_likelihood/partial_likelihood.py
satute/partial_likelihood/rate_matrix.py
satute/rate_analysis.py
satute/satute_file/file_writer.py
satute/satute_file/satute_file_writer.py
satute/sequences.py
satute/spectral_decomposition.py
satute/trees.py
satute/valid_data_input.py
satute/ztest_posterior_distribution.py
satute-1.0.7.dist-info/METADATA
satute-1.0.7.dist-info/WHEEL
satute-1.0.7.dist-info/entry_points.txt
satute-1.0.7.dist-info/RECORD
