Metadata-Version: 2.1
Name: satute
Version: 1.0.7
Summary: SatuTe (Saturation Test) is a Python-based tool designed to test for phylogenetic information in phylogenetic analyses. The absence of phylogenetic information can be considered saturation. In two sequences, saturation occurs when multiple substitutions obscure the true genetic distances, potentially leading to artifacts and errors.
Home-page: https://github.com/Elli-ellgard/SatuTe
License: MIT
Keywords: bioinformatics,phylogenetics,saturation test,phylogenetic analysis
Author: CIBIV
Requires-Python: >=3.9,<4.0
Classifier: Intended Audience :: Science/Research
Classifier: License :: OSI Approved :: MIT License
Classifier: Programming Language :: Python :: 3
Classifier: Programming Language :: Python :: 3.9
Classifier: Programming Language :: Python :: 3.10
Classifier: Programming Language :: Python :: 3.11
Classifier: Programming Language :: Python :: 3.12
Classifier: Topic :: Scientific/Engineering :: Bio-Informatics
Requires-Dist: biopython (>=1.83,<2.0)
Requires-Dist: ete3 (>=3.1.3,<4.0.0)
Requires-Dist: numpy (>=1.26.4,<2.0.0)
Requires-Dist: pandas (>=2.2.2,<3.0.0)
Requires-Dist: scipy (>=1.13.0,<2.0.0)
Project-URL: documentation, https://github.com/Elli-ellgard/SatuTe/blob/main/docs/SatuTe_Manual.pdf
